libs/__init__.py
libs/canvas.py
libs/colorDialog.py
libs/combobox.py
libs/constants.py
libs/create_ml_io.py
libs/hashableQListWidgetItem.py
libs/labelDialog.py
libs/labelFile.py
libs/pascal_voc_io.py
libs/resources.py
libs/settings.py
libs/shape.py
libs/stringBundle.py
libs/toolBar.py
libs/ustr.py
libs/utils.py
libs/yolo_io.py
libs/zoomWidget.py
mlabelImg/__init__.py
mlabelImg/mlabelImg.py
mlabelImg-1.8.9.post2.dist-info/LICENSE
mlabelImg-1.8.9.post2.dist-info/METADATA
mlabelImg-1.8.9.post2.dist-info/WHEEL
mlabelImg-1.8.9.post2.dist-info/entry_points.txt
mlabelImg-1.8.9.post2.dist-info/top_level.txt
mlabelImg-1.8.9.post2.dist-info/RECORD
