Metadata-Version: 2.2
Name: mlabelImg
Version: 1.8.9.post2
Summary: LabelImg is a graphical image annotation tool and label object bounding boxes in images (Modified Version)
Home-page: https://github.com/PD-Mera/mlabelImg
Author: PD-Mera
Author-email: phuongdong1772000@gmail.com
License: MIT license
Keywords: labelImg labelTool development annotation deeplearning
Classifier: Development Status :: 5 - Production/Stable
Classifier: Intended Audience :: Developers
Classifier: License :: OSI Approved :: MIT License
Classifier: Natural Language :: English
Classifier: Programming Language :: Python :: 3
Classifier: Programming Language :: Python :: 3.3
Classifier: Programming Language :: Python :: 3.4
Classifier: Programming Language :: Python :: 3.5
Classifier: Programming Language :: Python :: 3.6
Classifier: Programming Language :: Python :: 3.7
Requires-Python: >=3.0.0
License-File: LICENSE
Requires-Dist: pyqt5
Requires-Dist: lxml
Dynamic: author
Dynamic: author-email
Dynamic: classifier
Dynamic: description
Dynamic: description-content-type
Dynamic: home-page
Dynamic: keywords
Dynamic: license
Dynamic: requires-dist
Dynamic: requires-python
Dynamic: summary
